advertising/__init__.py
advertising/abstract_request.py
advertising/auth.py
advertising/client.py
advertising/config.py
advertising/resources/__init__.py
advertising/resources/portfolios.py
advertising/resources/profiles.py
advertising/resources/sb/__init__.py
advertising/resources/sb/keyword_recommendations.py
advertising/resources/sp/__init__.py
advertising/resources/sp/ad_group_keywords.py
advertising/resources/sp/ad_group_negative_keywords.py
advertising/resources/sp/ad_groups.py
advertising/resources/sp/bidding.py
advertising/resources/sp/campaign_negative_keywords.py
advertising/resources/sp/campaigns.py
advertising/resources/sp/product_ads.py
advertising/resources/sp/product_targeting.py
advertising/resources/sp/reports.py
advertising/resources/sp/snapshots.py
advertising/resources/sp/suggested_keywords.py
amazon_advertising-1.0.3.dist-info/METADATA
amazon_advertising-1.0.3.dist-info/WHEEL
amazon_advertising-1.0.3.dist-info/top_level.txt
amazon_advertising-1.0.3.dist-info/RECORD
