Metadata-Version: 2.1
Name: amazon-advertising
Version: 1.0.3
Summary: simple Amazon Advertising API client
Home-page: https://gitlab.com/ketu.lai/amazon-advertising
Author: ketu.lai
Author-email: ketu.lai@gmail.com
License: MIT
Keywords: amazon advertising api
Platform: UNKNOWN
Requires-Python: >=3.6
